crwlr/__init__.py
crwlr/command_line.py
crwlr/crossref.py
crwlr/database.py
crwlr/errors.py
crwlr/helper.py
crwlr/scopus.py
crwlr/springer.py
crwlr/statics.py
crwlr/types.py
crwlr/wiley.py
crwlr/xploreapi.py
crwlr-0.2.1.dist-info/AUTHORS
crwlr-0.2.1.dist-info/LICENSE
crwlr-0.2.1.dist-info/METADATA
crwlr-0.2.1.dist-info/WHEEL
crwlr-0.2.1.dist-info/entry_points.txt
crwlr-0.2.1.dist-info/top_level.txt
crwlr-0.2.1.dist-info/RECORD
