Metadata-Version: 2.1
Name: crwlr
Version: 0.2.1
Summary: Data Mining artifact for publication dbs
Home-page: UNKNOWN
Author: Nico H.
Author-email: e1129267@student.tuwien.ac.at
License: UNKNOWN
Platform: UNKNOWN
Requires-Python: >=3.6
Requires-Dist: certifi (==2020.4.5.1)
Requires-Dist: chardet (==3.0.4)
Requires-Dist: configparser (==5.0.0)
Requires-Dist: crossref-commons (==0.0.7)
Requires-Dist: entrypoints (==0.3)
Requires-Dist: idna (==2.9)
Requires-Dist: lxml (==4.5.0)
Requires-Dist: mysqlclient (==1.4.6)
Requires-Dist: numpy (==1.18.4)
Requires-Dist: pandas (==1.0.3)
Requires-Dist: pybliometrics (==2.4.0)
Requires-Dist: python-dateutil (==2.8.1)
Requires-Dist: pytz (==2020.1)
Requires-Dist: ratelimit (==2.2.1)
Requires-Dist: requests (==2.23.0)
Requires-Dist: rispy (==0.5.0)
Requires-Dist: simplejson (==3.17.0)
Requires-Dist: six (==1.14.0)
Requires-Dist: SQLAlchemy (==1.3.16)
Requires-Dist: urllib3 (==1.25.9)
Requires-Dist: xmltodict (==0.12.0)
